windmillartifactv1/__init__.py
windmillartifactv1/client/__init__.py
windmillartifactv1/client/artifact_api_artifact.py
windmillartifactv1/client/artifact_client.py
windmillartifactv1/client/paging.py
windmillartifactv1/tools/__init__.py
windmillartifactv1/tools/download_artifact.py
windmill_artifact-1.0.0.27.dist-info/METADATA
windmill_artifact-1.0.0.27.dist-info/WHEEL
windmill_artifact-1.0.0.27.dist-info/top_level.txt
windmill_artifact-1.0.0.27.dist-info/RECORD
