Metadata-Version: 2.1
Name: windmill-artifact
Version: 1.0.0.27
Summary: sdk in python for windmill artifact
Home-page: http://www.ai.com
Author: yangtingyu01
License: MIT
Classifier: Programming Language :: Python
Classifier: Programming Language :: Python :: 3
Classifier: Programming Language :: Python :: 3.7
Classifier: Programming Language :: Python :: 3.8
Classifier: Programming Language :: Python :: 3.9
Requires-Python: >=3.6
Requires-Dist: bce-python-sdk==0.8.87
Requires-Dist: bce-internal-sdk
